Metadata-Version: 2.1
Name: aitoolsAPI
Version: 0.2
Summary: A lightweight library that makes it easy to use Stable Diffusion XL and GPT.
Home-page: http://github.com/Master05710/aitoolsAPI
Author: Opo
Author-email: admin@opo.k.vu
License: MIT
Platform: UNKNOWN
